neatmesh/__init__.py
neatmesh/_analyzer.py
neatmesh/_cli.py
neatmesh/_common.py
neatmesh/_exceptions.py
neatmesh/_geometry.py
neatmesh/_mesh.py
neatmesh/_reader.py
neatmesh/_reporter.py
neatmesh-0.0.8.dist-info/LICENSE
neatmesh-0.0.8.dist-info/METADATA
neatmesh-0.0.8.dist-info/WHEEL
neatmesh-0.0.8.dist-info/entry_points.txt
neatmesh-0.0.8.dist-info/top_level.txt
neatmesh-0.0.8.dist-info/RECORD
