Metadata-Version: 2.1
Name: neatmesh
Version: 0.0.8
Summary: Finite Volume Mesh Quality Inspector
Home-page: https://github.com/eigemx/neatmesh
Author: Mohamed Emara
Author-email: mae.emara@gmail.com
Project-URL: Bug Tracker, https://github.com/eigemx/neatmesh/issues
Keywords: mesh,scientific,engineering,fvm,fem,finite volume,finite element
Classifier: Programming Language :: Python :: 3
Classifier: License :: OSI Approved :: MIT License
Classifier: Operating System :: OS Independent
Requires-Python: >=3.8
License-File: LICENSE
Requires-Dist: numpy
Requires-Dist: rich
Requires-Dist: meshio
Requires-Dist: humanize
Requires-Dist: toml
Requires-Dist: importlib-metadata ; python_version < "3.8"
